deepfake_gitract/__init__.py
deepfake_gitract/deepfake_gitract.py
deepfake_gitract-1.0.2.dist-info/LICENSE
deepfake_gitract-1.0.2.dist-info/METADATA
deepfake_gitract-1.0.2.dist-info/WHEEL
deepfake_gitract-1.0.2.dist-info/top_level.txt
deepfake_gitract-1.0.2.dist-info/RECORD
